{
  "bundler": "rollup",
  "shimport": "2.0.4",
  "assets": {
    "main": "client.11904187.js"
  },
  "css": {
    "main": [
      "client-e49779fb.css"
    ]
  },
  "dependencies": {
    "index.svelte": [
      "index.4c00d398.js",
      "SvelteSeo.97b8070c.js",
      "inject_styles.5607aec6.js",
      "index-6a2bc968.css"
    ],
    "newsLetter/index.svelte": [
      "index.3b8599df.js",
      "inject_styles.5607aec6.js",
      "index-9d07180b.css"
    ],
    "collectif/index.svelte": [
      "index.86b67b65.js",
      "SvelteSeo.97b8070c.js",
      "bundle.esm.a297de33.js",
      "inject_styles.5607aec6.js",
      "index-ebbaaf4b.css"
    ],
    "contact/index.svelte": [
      "index.4d15e9f2.js",
      "bundle.esm.a297de33.js",
      "inject_styles.5607aec6.js",
      "index-f9423815.css"
    ],
    "cgvcgu/index.svelte": [
      "index.ffc62751.js",
      "snarkdown.es.257e5e6b.js",
      "bundle.esm.a297de33.js",
      "inject_styles.5607aec6.js",
      "index-f272817a.css"
    ],
    "presse/index.svelte": [
      "index.7f50b18a.js",
      "SvelteSeo.97b8070c.js",
      "bundle.esm.a297de33.js",
      "inject_styles.5607aec6.js",
      "index-93e0e21b.css"
    ],
    "projet/[slug].svelte": [
      "[slug].b2873b67.js",
      "SvelteSeo.97b8070c.js",
      "snarkdown.es.257e5e6b.js",
      "bundle.esm.a297de33.js",
      "inject_styles.5607aec6.js",
      "[slug]-af9b0efe.css"
    ],
    "blast/index.svelte": [
      "index.0884f74b.js",
      "SvelteSeo.97b8070c.js",
      "bundle.esm.a297de33.js",
      "inject_styles.5607aec6.js",
      "index-f53b6465.css"
    ],
    "video/index.svelte": [
      "index.dd80bbf2.js",
      "SvelteSeo.97b8070c.js",
      "bundle.esm.a297de33.js",
      "inject_styles.5607aec6.js",
      "index-435808ef.css"
    ],
    "news/index.svelte": [
      "index.85c00923.js",
      "snarkdown.es.257e5e6b.js",
      "bundle.esm.a297de33.js",
      "inject_styles.5607aec6.js",
      "index-dee627eb.css"
    ],
    "shop/index.svelte": [
      "index.00ba0adc.js",
      "SvelteSeo.97b8070c.js",
      "bundle.esm.a297de33.js",
      "inject_styles.5607aec6.js",
      "index-4525c145.css"
    ]
  },
  "legacy_assets": {
    "main": "client.d30cddf7.js"
  }
}