{
  "bundler": "rollup",
  "shimport": "2.0.4",
  "assets": {
    "main": "client.a7fe2b82.js"
  },
  "css": {
    "main": [
      "client-f7115c0d.css"
    ]
  },
  "dependencies": {
    "index.svelte": [
      "index.64fe3e03.js",
      "SvelteSeo.bb62bdd9.js",
      "inject_styles.5607aec6.js",
      "index-6a2bc968.css"
    ],
    "newsLetter/index.svelte": [
      "index.d5229a69.js",
      "inject_styles.5607aec6.js",
      "index-9d07180b.css"
    ],
    "collectif/index.svelte": [
      "index.b7ee26ea.js",
      "SvelteSeo.bb62bdd9.js",
      "bundle.esm.a297de33.js",
      "inject_styles.5607aec6.js",
      "index-ebbaaf4b.css"
    ],
    "contact/index.svelte": [
      "index.54c25559.js",
      "bundle.esm.a297de33.js",
      "inject_styles.5607aec6.js",
      "index-f9423815.css"
    ],
    "cgvcgu/index.svelte": [
      "index.4848155b.js",
      "snarkdown.es.257e5e6b.js",
      "bundle.esm.a297de33.js",
      "inject_styles.5607aec6.js",
      "index-f272817a.css"
    ],
    "presse/index.svelte": [
      "index.56a46ae3.js",
      "SvelteSeo.bb62bdd9.js",
      "bundle.esm.a297de33.js",
      "inject_styles.5607aec6.js",
      "index-93e0e21b.css"
    ],
    "projet/[slug].svelte": [
      "[slug].61fd81f0.js",
      "SvelteSeo.bb62bdd9.js",
      "snarkdown.es.257e5e6b.js",
      "bundle.esm.a297de33.js",
      "inject_styles.5607aec6.js",
      "[slug]-af9b0efe.css"
    ],
    "blast/index.svelte": [
      "index.f123a089.js",
      "SvelteSeo.bb62bdd9.js",
      "bundle.esm.a297de33.js",
      "inject_styles.5607aec6.js",
      "index-f53b6465.css"
    ],
    "video/index.svelte": [
      "index.34d8aacf.js",
      "SvelteSeo.bb62bdd9.js",
      "bundle.esm.a297de33.js",
      "inject_styles.5607aec6.js",
      "index-435808ef.css"
    ],
    "news/index.svelte": [
      "index.8ea92d26.js",
      "snarkdown.es.257e5e6b.js",
      "bundle.esm.a297de33.js",
      "inject_styles.5607aec6.js",
      "index-b1f9e689.css"
    ],
    "shop/index.svelte": [
      "index.95fa0795.js",
      "SvelteSeo.bb62bdd9.js",
      "bundle.esm.a297de33.js",
      "inject_styles.5607aec6.js",
      "index-4525c145.css"
    ]
  },
  "legacy_assets": {
    "main": "client.3a20442f.js"
  }
}